CHANGES
LICENSE
MANIFEST.in
README
setup.cfg
setup.py
demo/plot_demo.py
demo/rnotebook.py
pynotebook/__init__.py
pynotebook/cerealizerformat.py
pynotebook/clients.py
pynotebook/controlled.py
pynotebook/graphics.py
pynotebook/inspector.py
pynotebook/nbbuilder.py
pynotebook/nbstream.py
pynotebook/nbtexels.py
pynotebook/nbview.py
pynotebook/pyclient.py
pynotebook/textformat.py
pynotebook.egg-info/PKG-INFO
pynotebook.egg-info/SOURCES.txt
pynotebook.egg-info/dependency_links.txt
pynotebook.egg-info/requires.txt
pynotebook.egg-info/top_level.txt
pynotebook/textmodel/__init__.py
pynotebook/textmodel/modelbase.py
pynotebook/textmodel/properties.py
pynotebook/textmodel/styles.py
pynotebook/textmodel/texeltree.py
pynotebook/textmodel/textmodel.py
pynotebook/textmodel/viewbase.py
pynotebook/textmodel/weights.py
pynotebook/wxtextview/__init__.py
pynotebook/wxtextview/boxes.py
pynotebook/wxtextview/builder.py
pynotebook/wxtextview/linewrap.py
pynotebook/wxtextview/rect.py
pynotebook/wxtextview/simplelayout.py
pynotebook/wxtextview/testdevice.py
pynotebook/wxtextview/testing.py
pynotebook/wxtextview/textview.py
pynotebook/wxtextview/wxdevice.py
pynotebook/wxtextview/wxtextview.py