Metadata-Version: 2.1
Name: pynotebook
Version: 0.3.0
Summary: A wxPython based notebook environment for interactive computing.
Home-page: https://github.com/chrisecker/pynotebook
Author: C. Ecker
Author-email: textmodelview@gmail.com
License: BSD
Keywords: Interactive,Interpreter,Notebook,Shell,wxPython
Classifier: Intended Audience :: Developers
Classifier: Intended Audience :: System Administrators
Classifier: Intended Audience :: Science/Research
Classifier: License :: OSI Approved :: BSD License
Classifier: Programming Language :: Python
Classifier: Programming Language :: Python :: 3.0
License-File: LICENSE
